.gitignore
LICENSE.md
README.rst
requirements.txt
setup.py
spotify2musicbrainz.py
spotify2musicbrainz.egg-info/PKG-INFO
spotify2musicbrainz.egg-info/SOURCES.txt
spotify2musicbrainz.egg-info/dependency_links.txt
spotify2musicbrainz.egg-info/entry_points.txt
spotify2musicbrainz.egg-info/requires.txt
spotify2musicbrainz.egg-info/top_level.txt