Metadata-Version: 1.1
Name: spotify2musicbrainz
Version: 0.3.2
Summary: An aid to add information from Spotify to MusicBrainz.
Home-page: https://gitlab.com/Freso/spotify2musicbrainz
Author: Frederik “Freso” S. Olesen
Author-email: spotify2musicbrainz@freso.dk
License: GPLv3+
Keywords: spotify musicbrainz music metadata data
Platform: UNKNOWN
Classifier: Development Status :: 3 - Alpha
Classifier: Environment :: Console
Classifier: Intended Audience :: End Users/Desktop
Classifier: License :: OSI Approved :: GNU General Public License v3 or later (GPLv3+)
Classifier: Natural Language :: English
Classifier: Programming Language :: Python :: 3
Classifier: Programming Language :: Python :: 3 :: Only
Classifier: Topic :: Multimedia :: Sound/Audio
Classifier: Topic :: Utilities
